mir/msmtpq.py
mir/msmtpq/__init__.py
mir/msmtpq/__main__.py
mir/msmtpq/main.py
mir/msmtpq/queue.py
mir/msmtpq/sendmail.py
mir.msmtpq-1.0.0.dist-info/DESCRIPTION.rst
mir.msmtpq-1.0.0.dist-info/METADATA
mir.msmtpq-1.0.0.dist-info/RECORD
mir.msmtpq-1.0.0.dist-info/WHEEL
mir.msmtpq-1.0.0.dist-info/entry_points.txt
mir.msmtpq-1.0.0.dist-info/metadata.json
mir.msmtpq-1.0.0.dist-info/top_level.txt
