Metadata-Version: 2.0
Name: mir.msmtpq
Version: 1.0.0
Summary: Message queue for msmtp
Home-page: https://github.com/darkfeline/mir.msmtpq
Author: Allen Li
Author-email: darkfeline@felesatra.moe
License: UNKNOWN
Platform: UNKNOWN
Classifier: Development Status :: 5 - Production/Stable
Classifier: Environment :: Console
Classifier: Intended Audience :: End Users/Desktop
Classifier: License :: OSI Approved :: Apache Software License
Classifier: Programming Language :: Python :: 3.5
